<collection xmlns="http://exist.sourceforge.net/NS/exist" name="/db/framework/bungeni/admin" owner="admin" group="dba" mode="644" created="2012-01-17T13:38:28+03:00" version="1">
    <acl entries="0" version="1"/>
    <resource type="XMLResource" name="admin-download-subform.xml" owner="admin" group="dba" mode="644" created="2012-03-07T13:25:10+03:00" modified="2012-03-07T13:25:10+03:00" filename="admin-download-subform.xml" mimetype="application/xml">
        <acl entries="0" version="1"/>
    </resource>
    <resource type="BinaryResource" name="admin-download.xql" owner="admin" group="dba" mode="644" created="2012-01-19T13:37:03+03:00" modified="2012-03-07T13:33:09+03:00" filename="admin-download.xql" mimetype="application/xquery">
        <acl entries="0" version="1"/>
    </resource>
    <resource type="XMLResource" name="admin-navigation-subform.xml" owner="admin" group="dba" mode="644" created="2012-03-07T10:18:19+03:00" modified="2012-03-07T10:18:19+03:00" filename="admin-navigation-subform.xml" mimetype="application/xml">
        <acl entries="0" version="1"/>
    </resource>
    <resource type="XMLResource" name="admin-navigation.xml" owner="admin" group="dba" mode="644" created="2012-01-17T12:44:53+03:00" modified="2012-01-17T12:44:53+03:00" filename="admin-navigation.xml" mimetype="application/xml">
        <acl entries="0" version="1"/>
    </resource>
    <resource type="BinaryResource" name="admin-navigation.xql" owner="admin" group="dba" mode="644" created="2012-03-05T18:04:20+03:00" modified="2012-03-07T13:15:52+03:00" filename="admin-navigation.xql" mimetype="application/xquery">
        <acl entries="0" version="1"/>
    </resource>
    <resource type="XMLResource" name="admin-order-subform.xml" owner="admin" group="dba" mode="645" created="2012-03-07T11:58:54+03:00" modified="2012-03-07T11:58:54+03:00" filename="admin-order-subform.xml" mimetype="application/xml">
        <acl entries="0" version="1"/>
    </resource>
    <resource type="BinaryResource" name="admin-order.xql" owner="admin" group="dba" mode="645" created="2012-01-17T12:44:53+03:00" modified="2012-03-07T13:42:49+03:00" filename="admin-order.xql" mimetype="application/xquery">
        <acl entries="0" version="1"/>
    </resource>
    <resource type="BinaryResource" name="admin-pagination.xql" owner="admin" group="dba" mode="644" created="2012-01-13T17:17:15+03:00" modified="2012-03-06T17:38:55+03:00" filename="admin-pagination.xql" mimetype="application/xquery">
        <acl entries="0" version="1"/>
    </resource>
    <resource type="XMLResource" name="admin-route-add.xml" owner="admin" group="dba" mode="644" created="2012-03-06T16:23:17+03:00" modified="2012-03-06T16:23:17+03:00" filename="admin-route-add.xml" mimetype="application/xml">
        <acl entries="0" version="1"/>
    </resource>
    <resource type="XMLResource" name="admin-route-subform.xml" owner="admin" group="dba" mode="644" created="2012-01-17T12:44:53+03:00" modified="2012-01-17T12:44:53+03:00" filename="admin-route-subform.xml" mimetype="application/xml">
        <acl entries="0" version="1"/>
    </resource>
    <resource type="BinaryResource" name="admin-route.xql" owner="admin" group="dba" mode="644" created="2012-01-17T12:44:53+03:00" modified="2012-03-07T16:26:36+03:00" filename="admin-route.xql" mimetype="application/xquery">
        <acl entries="0" version="1"/>
    </resource>
    <resource type="XMLResource" name="admin-search-subform.xml" owner="admin" group="dba" mode="644" created="2012-03-07T12:12:25+03:00" modified="2012-03-07T12:12:25+03:00" filename="admin-search-subform.xml" mimetype="application/xml">
        <acl entries="0" version="1"/>
    </resource>
    <resource type="BinaryResource" name="admin-search.xql" owner="admin" group="dba" mode="744" created="2012-01-17T18:15:07+03:00" modified="2012-03-07T13:36:18+03:00" filename="admin-search.xql" mimetype="application/xquery">
        <acl entries="0" version="1"/>
    </resource>
    <resource type="XMLResource" name="admin-tabgroup-subform.xml" owner="admin" group="dba" mode="644" created="2012-03-06T15:40:26+03:00" modified="2012-03-06T15:40:26+03:00" filename="admin-tabgroup-subform.xml" mimetype="application/xml">
        <acl entries="0" version="1"/>
    </resource>
    <resource type="BinaryResource" name="admin-tabgroup.xql" owner="admin" group="dba" mode="644" created="2012-01-19T09:41:25+03:00" modified="2012-03-07T13:35:04+03:00" filename="admin-tabgroup.xql" mimetype="application/xquery">
        <acl entries="0" version="1"/>
    </resource>
    <resource type="XMLResource" name="admin-ui.xml" owner="admin" group="dba" mode="644" created="2012-01-13T17:17:15+03:00" modified="2012-01-13T17:17:15+03:00" filename="admin-ui.xml" mimetype="application/xml">
        <acl entries="0" version="1"/>
    </resource>
    <resource type="BinaryResource" name="admin.xqm" owner="admin" group="dba" mode="644" created="2012-01-18T12:22:13+03:00" modified="2012-03-07T11:15:21+03:00" filename="admin.xqm" mimetype="application/xquery">
        <acl entries="0" version="1"/>
    </resource>
    <resource type="BinaryResource" name="controller.xql" owner="admin" group="dba" mode="644" created="2012-02-26T17:38:11+03:00" modified="2012-02-26T17:40:04+03:00" filename="controller.xql" mimetype="application/xquery">
        <acl entries="0" version="1"/>
    </resource>
    <resource type="BinaryResource" name="help.xql" owner="admin" group="dba" mode="644" created="2012-03-07T11:24:40+03:00" modified="2012-03-07T16:48:05+03:00" filename="help.xql" mimetype="application/xquery">
        <acl entries="0" version="1"/>
    </resource>
    <resource type="BinaryResource" name="index.xql" owner="admin" group="dba" mode="644" created="2012-01-20T12:43:26+03:00" modified="2012-03-06T18:06:10+03:00" filename="index.xql" mimetype="application/xquery">
        <acl entries="0" version="1"/>
    </resource>
</collection>